Metadata-Version: 2.1
Name: odoo-addon-stock_move_purchase_price_update
Version: 15.0.1.0.0.3
Summary: Allow update purchase price from incoming picking operations
Home-page: https://github.com/OCA/purchase-workflow
Author: Tecnativa, Odoo Community Association (OCA)
Author-email: support@odoo-community.org
License: AGPL-3
Classifier: Programming Language :: Python
Classifier: Framework :: Odoo
Classifier: Framework :: Odoo :: 15.0
Classifier: License :: OSI Approved :: GNU Affero General Public License v3
Classifier: Development Status :: 4 - Beta
Requires-Python: >=3.8
Requires-Dist: odoo<15.1dev,>=15.0a
